baicai_webui/__init__.py
baicai_webui/app.py
baicai_webui/cli.py
baicai_webui/components/base_page.py
baicai_webui/components/button_graph.py
baicai_webui/components/chat/__init__.py
baicai_webui/components/chat/ai_assistant.py
baicai_webui/components/chat/ai_tutor.py
baicai_webui/components/image_viewer.py
baicai_webui/components/llm_settings.py
baicai_webui/components/model/__init__.py
baicai_webui/components/model/data_upload.py
baicai_webui/components/model/draw.py
baicai_webui/components/model/graph_executor.py
baicai_webui/components/model/model_config_form.py
baicai_webui/components/model/model_config_page.py
baicai_webui/components/model/model_settings.py
baicai_webui/components/model/result_display.py
baicai_webui/components/model/tabular_shap.py
baicai_webui/components/model/training.py
baicai_webui/components/right_sidebar.py
baicai_webui/components/stepper.py
baicai_webui/components/tutor/__init__.py
baicai_webui/components/tutor/book_chapters.py
baicai_webui/components/tutor/multi_choice_questions.py
baicai_webui/components/tutor/survey.py
baicai_webui/components/tutor/text_selection.py
baicai_webui/pages/book.py
baicai_webui/pages/collab.py
baicai_webui/pages/home.py
baicai_webui/pages/llm_setting.py
baicai_webui/pages/ml.py
baicai_webui/pages/nlp.py
baicai_webui/pages/quiz.py
baicai_webui/pages/try.py
baicai_webui/pages/vision.py
baicai_webui/utils.py
baicai_webui-0.1.2.dist-info/METADATA
baicai_webui-0.1.2.dist-info/WHEEL
baicai_webui-0.1.2.dist-info/entry_points.txt
baicai_webui-0.1.2.dist-info/RECORD
