Metadata-Version: 2.3
Name: baicai-webui
Version: 0.1.2
Summary: WebUI for Baicai
License: MIT
Keywords: python,agent,AI,machine learning,LLM
Author: Zhaoyang tech
Author-email: gengyabc@aliyun.com
Requires-Python: >=3.10,<3.12
Classifier: License :: OSI Approved :: MIT License
Classifier: Programming Language :: Python :: 3
Classifier: Programming Language :: Python :: 3.10
Classifier: Programming Language :: Python :: 3.11
Requires-Dist: baicai-base (==0.1.2)
Requires-Dist: baicai-dev (==0.1.0)
Requires-Dist: baicai-tutor (==0.1.0)
Requires-Dist: streamlit (>=1.43.0,<2.0.0)
Requires-Dist: streamlit-flow-component (>=1.6.1,<2.0.0)
Requires-Dist: streamlit-markmap (>=1.0.1,<2.0.0)
Requires-Dist: streamlit-mermaid (>=0.3.0,<0.4.0)
Requires-Dist: streamlit-pdf-viewer (>=0.0.26,<0.0.27)
